{
  "daily": {
    "Produced": [
      { "x": 0, "y": 130.5 },
      { "x": 1, "y": 220.7 },
      { "x": 2, "y": 350.8 },
      { "x": 3, "y": 420.0 },
      { "x": 4, "y": 610.2 }
    ],
    "Consumed": [
      { "x": 0, "y": 110.2 },
      { "x": 1, "y": 190.8 },
      { "x": 2, "y": 290.3 },
      { "x": 3, "y": 360.0 },
      { "x": 4, "y": 460.5 }
    ],
    "ImpExp": [
      { "x": 0, "y": 25.0 },
      { "x": 1, "y": 35.6 },
      { "x": 2, "y": 65.0 },
      { "x": 3, "y": 55.2 },
      { "x": 4, "y": 160.1 }
    ]
  },
  "weekly": {
    "Produced": [
      { "x": 0, "y": 520.3 },
      { "x": 1, "y": 710.1 },
      { "x": 2, "y": 920.4 },
      { "x": 3, "y": 820.9 },
      { "x": 4, "y": 960.5 },
      { "x": 5, "y": 1120.6 },
      { "x": 6, "y": 1240.7 }
    ],
    "Consumed": [
      { "x": 0, "y": 460.7 },
      { "x": 1, "y": 660.2 },
      { "x": 2, "y": 820.0 },
      { "x": 3, "y": 760.5 },
      { "x": 4, "y": 870.8 },
      { "x": 5, "y": 1030.3 },
      { "x": 6, "y": 1160.2 }
    ],
    "ImpExp": [
      { "x": 0, "y": 60.0 },
      { "x": 1, "y": 65.4 },
      { "x": 2, "y": 105.3 },
      { "x": 3, "y": 55.8 },
      { "x": 4, "y": 110.0 },
      { "x": 5, "y": 110.5 },
      { "x": 6, "y": 58.6 }
    ]
  },
  "monthly": {
    "Produced": [
      { "x": 0, "y": 1600.8 },
      { "x": 1, "y": 2600.5 },
      { "x": 2, "y": 3100.7 },
      { "x": 3, "y": 3600.6 },
      { "x": 4, "y": 4100.2 },
      { "x": 5, "y": 4600.4 }
    ],
    "Consumed": [
      { "x": 0, "y": 1500.2 },
      { "x": 1, "y": 2400.1 },
      { "x": 2, "y": 3000.3 },
      { "x": 3, "y": 3500.9 },
      { "x": 4, "y": 3900.6 },
      { "x": 5, "y": 4300.7 }
    ],
    "ImpExp": [
      { "x": 0, "y": 120.0 },
      { "x": 1, "y": 220.3 },
      { "x": 2, "y": 120.6 },
      { "x": 3, "y": 160.4 },
      { "x": 4, "y": 220.0 },
      { "x": 5, "y": 320.5 }
    ]
  },
  "yearly": {
    "Produced": [
      { "x": 0, "y": 19000.5 },
      { "x": 1, "y": 21000.3 },
      { "x": 2, "y": 22000.7 },
      { "x": 3, "y": 26000.2 },
      { "x": 4, "y": 28000.8 }
    ],
    "Consumed": [
      { "x": 0, "y": 17000.6 },
      { "x": 1, "y": 20000.4 },
      { "x": 2, "y": 21000.9 },
      { "x": 3, "y": 25000.7 },
      { "x": 4, "y": 27000.6 }
    ],
    "ImpExp": [
      { "x": 0, "y": 2200.0 },
      { "x": 1, "y": 1200.0 },
      { "x": 2, "y": 1200.3 },
      { "x": 3, "y": 1200.5 },
      { "x": 4, "y": 1600.7 }
    ]
  }
}
